pydirac/__init__.py
pydirac/analysis/__init__.py
pydirac/analysis/polarizability.py
pydirac/analysis/utility.py
pydirac/cli/__init__.py
pydirac/cli/pypam.py
pydirac/cli/pypam_atom_db.py
pydirac/core/__init__.py
pydirac/core/basis.py
pydirac/core/molecule.py
pydirac/core/orbitals.py
pydirac/core/periodic.py
pydirac/core/settings.py
pydirac/data/__init__.py
pydirac/data/__pycache__/__init__.cpython-310.pyc
pydirac/data/__pycache__/__init__.cpython-311.pyc
pydirac/data/basisset/dyall.acv3z
pydirac/data/basisset/dyall.acv4z
pydirac/data/basisset/dyall.cv3z
pydirac/data/basisset/dyall.cv4z
pydirac/data/template/AtomicDHFSet.yaml
pydirac/io/__init__.py
pydirac/io/inputs.py
pydirac/io/outputs.py
pydirac/io/sets.py
pydirac-2024.7.8.dist-info/LICENSE
pydirac-2024.7.8.dist-info/METADATA
pydirac-2024.7.8.dist-info/WHEEL
pydirac-2024.7.8.dist-info/entry_points.txt
pydirac-2024.7.8.dist-info/top_level.txt
pydirac-2024.7.8.dist-info/RECORD
