Metadata-Version: 2.1
Name: pydirac
Version: 2024.7.8
Summary: This tool provides a convenient solution for managing input and output files when using the DIRAC program for computational chemistry. With this tool, users can easily generate properly formatted input files and parse the output files to extract relevant information. It is designed to streamline the process of preparing input files and handling the output generated by DIRAC, saving users time and reducing the potential for errors.
Author-email: YingXing Cheng <yingxing.cheng@ugent.be>
License: GNU GENERAL PUBLIC LICENSE
Project-URL: Issues, https://github.com/yingxingcheng/pydirac/issues
Project-URL: Source, https://github.com/yingxingcheng/pydirac/
Project-URL: Changelog, https://github.com/yingxingcheng/pydirac/blob/main/CHANGELOG.md
Classifier: Development Status :: 3 - Alpha
Classifier: Environment :: Console
Classifier: Intended Audience :: Science/Research
Classifier: Intended Audience :: Education
Classifier: Framework :: Matplotlib
Classifier: License :: OSI Approved :: GNU General Public License v3 or later (GPLv3+)
Classifier: Natural Language :: English
Classifier: Operating System :: POSIX
Classifier: Operating System :: MacOS
Classifier: Programming Language :: Python :: 3
Classifier: Topic :: Scientific/Engineering
Classifier: Topic :: Text Processing
Requires-Python: >=3.6
License-File: LICENSE
Requires-Dist: monty
Requires-Dist: numpy
Requires-Dist: importlib-resources
Requires-Dist: ruamel.yaml
